ezr/__init__.py
ezr/__main__.py
ezr/ezr.py
ezr/ezrtest.py
ezr/stats.py
ezr-0.5.0.dist-info/licenses/LICENSE
ezr-0.5.0.dist-info/METADATA
ezr-0.5.0.dist-info/WHEEL
ezr-0.5.0.dist-info/entry_points.txt
ezr-0.5.0.dist-info/top_level.txt
ezr-0.5.0.dist-info/RECORD
